invert4geom/__init__.py
invert4geom/_version.py
invert4geom/_version.pyi
invert4geom/cross_validation.py
invert4geom/inversion.py
invert4geom/optimization.py
invert4geom/plotting.py
invert4geom/regional.py
invert4geom/synthetic.py
invert4geom/uncertainty.py
invert4geom/utils.py
invert4geom-1.1.0.dist-info/METADATA
invert4geom-1.1.0.dist-info/WHEEL
invert4geom-1.1.0.dist-info/licenses/AUTHORS.md
invert4geom-1.1.0.dist-info/licenses/LICENSE
invert4geom-1.1.0.dist-info/RECORD
