Metadata-Version: 2.4
Name: invert4geom
Version: 1.1.0
Summary: Constrained gravity inversion to recover the geometry of a density contrast.
Project-URL: Homepage, https://github.com/mdtanker/invert4geom
Project-URL: Documentation, https://invert4geom.readthedocs.io/
Project-URL: Bug Tracker, https://github.com/mdtanker/invert4geom/issues
Project-URL: Discussions, https://github.com/mdtanker/invert4geom/discussions
Project-URL: Changelog, https://invert4geom.readthedocs.io/en/latest/changelog.html
Author-email: Matt Tankersley <matt.d.tankersley@gmail.com>
License: Copyright 2023 Matt Tankersley
License-File: AUTHORS.md
License-File: LICENSE
Keywords: Moho,density,geology,geometry,geophysics,geoscience,gravity,inversion,sediment
Classifier: Development Status :: 1 - Planning
Classifier: Intended Audience :: Developers
Classifier: Intended Audience :: Science/Research
Classifier: License :: OSI Approved :: MIT License
Classifier: Operating System :: OS Independent
Classifier: Programming Language :: Python
Classifier: Programming Language :: Python :: 3
Classifier: Programming Language :: Python :: 3 :: Only
Classifier: Programming Language :: Python :: 3.11
Classifier: Programming Language :: Python :: 3.12
Classifier: Programming Language :: Python :: 3.13
Classifier: Topic :: Scientific/Engineering
Classifier: Typing :: Typed
Requires-Python: >=3.11
Requires-Dist: dask
Requires-Dist: deprecation
Requires-Dist: harmonica>=0.7
Requires-Dist: ipython>=8.13.0
Requires-Dist: ipywidgets
Requires-Dist: joblib
Requires-Dist: matplotlib>=3.7.0
Requires-Dist: nomkl; platform_system != 'Windows'
Requires-Dist: numba
Requires-Dist: numba-progress
Requires-Dist: numpy>=1.25.0
Requires-Dist: optuna>=4.0
Requires-Dist: pandas>=2.0.0
Requires-Dist: plotly
Requires-Dist: polartoolkit
Requires-Dist: pooch
Requires-Dist: psutil
Requires-Dist: pygmt
Requires-Dist: pykdtree
Requires-Dist: pyvista
Requires-Dist: rioxarray
Requires-Dist: scikit-learn>=1.3.0
Requires-Dist: scipy>=1.11.0
Requires-Dist: seaborn
Requires-Dist: torch
Requires-Dist: tqdm
Requires-Dist: trame
Requires-Dist: verde
Requires-Dist: xarray>=2023.4.0
Requires-Dist: xrft
